README.md
setup.py
train/__init__.py
train/policy.py
train/state.py
train/utils.py
train.egg-info/PKG-INFO
train.egg-info/SOURCES.txt
train.egg-info/dependency_links.txt
train.egg-info/not-zip-safe
train.egg-info/top_level.txt
train/agents/__init__.py
train/agents/base.py